pyccnn/__init__.py
pyccnn/core/__init__.py
pyccnn/core/_settings.py
pyccnn/core/activations.py
pyccnn/core/losses.py
pyccnn/core/model.py
pyccnn/core/monitor.py
pyccnn/core/parser.py
pyccnn/core/units/__init__.py
pyccnn/core/units/linear.py
pyccnn/core/units/perceptron.py
pyccnn/core/units/sklearn.py
pyccnn/core/units/unit.py
pyccnn/examples/__init__.py
pyccnn/examples/run_bayes.py
pyccnn/examples/run_encoder.py
pyccnn/examples/run_letters.py
pyccnn/examples/run_quantile.py
pyccnn/examples/run_regress.py
pyccnn/examples/run_spirals.py
pyccnn/examples/configs/__init__.py
pyccnn/examples/configs/bayes.ini
pyccnn/examples/configs/encoder.ini
pyccnn/examples/configs/letters.ini
pyccnn/examples/configs/quantile.ini
pyccnn/examples/configs/regress.ini
pyccnn/examples/configs/spirals.ini
pyccnn-1.0.dist-info/LICENSE
pyccnn-1.0.dist-info/METADATA
pyccnn-1.0.dist-info/WHEEL
pyccnn-1.0.dist-info/top_level.txt
pyccnn-1.0.dist-info/RECORD
