Metadata-Version: 2.1
Name: pyccnn
Version: 1.0
Summary: A package for building and training cascade correlation neural networks in tensorflow and scipy.
Home-page: https://github.com/mike-gimelfarb/cascade-correlation-neural-networks
Author: Michael Gimelfarb
Author-email: mike.gimelfarb@mail.utoronto.ca
License: MIT License
Classifier: Development Status :: 4 - Beta
Classifier: Intended Audience :: Science/Research
Classifier: License :: OSI Approved :: MIT License
Classifier: Natural Language :: English
Classifier: Operating System :: OS Independent
Classifier: Programming Language :: Python :: 3
Classifier: Topic :: Scientific/Engineering :: Artificial Intelligence
Requires-Python: >=3.8
License-File: LICENSE
Requires-Dist: numpy>=1.19.2
Requires-Dist: scipy>=1.6.2
Requires-Dist: scikit-learn
Requires-Dist: pandas>=1.2.4
Requires-Dist: seaborn>=0.11.1
Requires-Dist: matplotlib>=3.3.4
Requires-Dist: tqdm
Requires-Dist: tensorflow
